og_agent/__init__.py
og_agent/agent_api_server.py
og_agent/agent_builder.py
og_agent/agent_llm.py
og_agent/agent_server.py
og_agent/agent_setup.py
og_agent/base_agent.py
og_agent/base_stream_client.py
og_agent/grammar.bnf
og_agent/llama_agent.py
og_agent/llama_client.py
og_agent/mock_agent.py
og_agent/openai_agent.py
og_agent/prompt.py
og_agent/tokenizer.py
og_agent-0.5.3.dist-info/METADATA
og_agent-0.5.3.dist-info/WHEEL
og_agent-0.5.3.dist-info/entry_points.txt
og_agent-0.5.3.dist-info/top_level.txt
og_agent-0.5.3.dist-info/RECORD
