Metadata-Version: 2.1
Name: og-agent
Version: 0.5.3
Summary: Open source code interpreter agent
Home-page: https://github.com/dbpunk-labs/octogen
Author: imotai
Author-email: wangtaize@dbpunk.com
Requires-Dist: og-proto
Requires-Dist: og-kernel
Requires-Dist: og-sdk
Requires-Dist: grpcio-tools >=1.57.0
Requires-Dist: grpc-google-iam-v1 >=0.12.6
Requires-Dist: aiofiles
Requires-Dist: orm[sqlite]
Requires-Dist: python-dotenv
Requires-Dist: openai
Requires-Dist: aiohttp >=3.8.5
Requires-Dist: pydantic
Requires-Dist: tiktoken
Requires-Dist: fastapi
Requires-Dist: uvicorn
